flet_popupmenu/__init__.py
flet_popupmenu/popup_menu.py
flet_popupmenu-0.0.3.dist-info/licenses/LICENSE
flet_popupmenu-0.0.3.dist-info/METADATA
flet_popupmenu-0.0.3.dist-info/WHEEL
flet_popupmenu-0.0.3.dist-info/top_level.txt
flet_popupmenu-0.0.3.dist-info/RECORD
