Metadata-Version: 2.4
Name: flet-popupmenu
Version: 0.0.3
Summary: Popup menu component for Flet
Author-email: Ivan Gonzalez Valles <ivanartista96@gmail.com>
License: MIT License
Keywords: flet,python,ui,popup,menu
Classifier: Programming Language :: Python :: 3
Classifier: License :: OSI Approved :: MIT License
Classifier: Operating System :: OS Independent
Requires-Python: >=3.8
License-File: LICENSE
Requires-Dist: flet>=0.22
Dynamic: license-file
